{
  "$schema": "https://raw.githubusercontent.com/streetsidesoftware/cspell/main/cspell.schema.json",
  "version": "0.2",
  "language": "en",
  "dictionaries": ["csharp", "typescript", "powershell", "npm", "dotnet", "bash", "markdown"],
  "enableGlobDot": true,
  "minWordLength": 4,
  "allowCompoundWords": true,
  "useGitignore": true,
  "ignorePaths": [
    "node_modules/**",
    ".git/**",
    ".vs/**",
    ".artifacts/**",
    ".config/**",
    ".devcontainer/**",
    ".gitignore",
    ".gitattributes",
    "*.meta",
    "Samples~/**",
    "package-lock.json",
    "Library/**",
    "Temp/**",
    "Logs/**",
    "obj/**",
    "bin/**",
    "*.dll",
    "*.exe",
    "*.pdb",
    "*.log",
    "*.sln",
    "*.csproj",
    "**/*.g.cs",
    "Third Party Notices.md",
    "cspell-output.txt"
  ],
  "words": [
    "DxMessaging",
    "dxmessaging",
    "wallstop",
    "DXMSG",
    "Untargeted",
    "untargeted",
    "UNTARGETED",
    "dereg",
    "retarget",
    "Retarget",
    "Retargets",
    "Behaviour",
    "Behaviours",
    "behaviour",
    "MonoBehaviour",
    "ScriptableObject",
    "GameObject",
    "Mathf",
    "Dont",
    "HDRP",
    "uxml",
    "hlsl",
    "hlsli",
    "hlslinc",
    "urtshader",
    "initialisation",
    "serialised",
    "unityproj",
    "userprefs",
    "booproj",
    "finalizers",
    "methodimpl",
    "iequatable",
    "IEquatable",
    "inlinable",
    "inlines",
    "customisation",
    "Centralised",
    "Virtuals",
    "Centralises",
    "accessibilities",
    "creational",
    "deregistrations",
    "unregistrations",
    "Zenject",
    "ZENJECT",
    "zenject",
    "Extenject",
    "extenject",
    "VContainer",
    "vcontainer",
    "VCONTAINER",
    "Reflex",
    "Cysharp",
    "cysharp",
    "UniRx",
    "WCAG",
    "openupm",
    "Pygments",
    "pygments",
    "kwds",
    "arithmatex",
    "linenums",
    "inlinehilite",
    "cairosvg",
    "UNIRX",
    "unirx",
    "Blazor",
    "nunit",
    "NUnit",
    "NUNIT",
    "Paket",
    "paket",
    "rhysd",
    "stefanzweifel",
    "ibiqlik",
    "gustavopsantos",
    "svermeulen",
    "hadashikick",
    "neuecc",
    "yzhang",
    "Anson",
    "csdevkit",
    "NOLOGO",
    "ncdu",
    "procs",
    "PROCS",
    "tokei",
    "TOKEI",
    "venv",
    "ifne",
    "nographics",
    "batchmode",
    "shellcheck",
    "actionlint",
    "csharpier",
    "csharpierignore",
    "csharpierrc",
    "pipx",
    "mkdocs",
    "pymdownx",
    "superfences",
    "twemoji",
    "slugify",
    "libz",
    "asmdef",
    "asmref",
    "asax",
    "axaml",
    "cppm",
    "cxxm",
    "paml",
    "resw",
    "resx",
    "xamlx",
    "vcproj",
    "dbproj",
    "lsproj",
    "wixproj",
    "wwaproj",
    "vspscc",
    "vssscc",
    "pidb",
    "ipch",
    "opendb",
    "opensdf",
    "psess",
    "vspx",
    "csdef",
    "dbmdl",
    "ntvs",
    "pycache",
    "publishproj",
    "astextplain",
    "SLRU",
    "Slru",
    "RAII",
    "raii",
    "Configurator",
    "Initializable",
    "Hipple",
    "lede",
    "mgmt",
    "Consulo",
    "consulo",
    "Unitysysinfo",
    "msysgit",
    "KHTML",
    "PTVS",
    "ACMR",
    "regen",
    "conv",
    "Hspec",
    "Pspec",
    "ebug",
    "elease",
    "eleases",
    "uild",
    "uilds",
    "ibrary",
    "ublish",
    "esult",
    "xpress",
    "checkin",
    "Segoe",
    "Noto",
    "Fira",
    "APFS",
    "NTFS",
    "nocasematch"
  ],
  "ignoreRegExpList": [
    "/[0-9a-fA-F]{8}-[0-9a-fA-F]{4}-[0-9a-fA-F]{4}-[0-9a-fA-F]{4}-[0-9a-fA-F]{12}/g",
    "/#[0-9a-fA-F]{6}([0-9a-fA-F]{2})?\\b/g",
    "/[0-9a-fA-F]{40}/g",
    "/[0-9a-fA-F]{64}/g",
    "/https?:\\/\\/[^\\s)\"'`>]+/g",
    "/[a-zA-Z0-9._%+-]+@[a-zA-Z0-9.-]+\\.[a-zA-Z]{2,}/g",
    "/\\{[0-9a-fA-F]{8}-[0-9a-fA-F]{4}-[0-9a-fA-F]{4}-[0-9a-fA-F]{4}-[0-9a-fA-F]{12}\\}/g"
  ]
}
